{
  "characterFrequency": {
    "a": 98668,
    "i": 137154,
    "n": 115309,
    "g": 66944,
    "o": 56135,
    "b": 14844,
    "e": 79485,
    "u": 78160,
    "c": 13193,
    "h": 71223,
    "d": 35916,
    "r": 10371,
    "f": 8498,
    "j": 22504,
    "k": 6341,
    "l": 18179,
    "v": 918,
    "m": 11472,
    "p": 3768,
    "q": 10591,
    "s": 31349,
    "t": 12950,
    "w": 12666,
    "x": 17668,
    "y": 31686,
    "z": 34007
  },
  "combinationFrequency": {
    " a": 1105,
    "a ": 14383,
    "ai": 10352,
    "i ": 64094,
    "an": 37031,
    "n ": 41692,
    "ng": 38699,
    "g ": 38699,
    "ao": 12100,
    "o ": 23753,
    " b": 11113,
    "ba": 2826,
    "be": 1428,
    "ei": 6627,
    "en": 17119,
    "bi": 2722,
    "ia": 18497,
    "ie": 3383,
    "e ": 33993,
    "in": 13973,
    "bo": 295,
    "bu": 3842,
    "u ": 32382,
    " c": 9877,
    "ca": 912,
    "ce": 356,
    "ch": 6746,
    "ha": 8543,
    "he": 13139,
    "hi": 13765,
    "ho": 5631,
    "on": 9666,
    "ou": 8605,
    "hu": 12242,
    "ua": 8111,
    "ui": 4695,
    "un": 2602,
    "uo": 8415,
    "ci": 858,
    "co": 536,
    "cu": 469,
    " d": 26888,
    "da": 6552,
    "de": 11848,
    "di": 3963,
    "iu": 2559,
    "do": 1650,
    "du": 2875,
    " e": 1968,
    "er": 1767,
    "r ": 1767,
    " f": 6362,
    "fa": 3161,
    "fe": 1676,
    "fo": 146,
    "fu": 1379,
    " g": 11417,
    "ga": 1804,
    "ge": 3087,
    "go": 1699,
    "gu": 4827,
    " h": 11019,
    " j": 16847,
    "ji": 14778,
    "io": 172,
    "ju": 2069,
    "ue": 2310,
    " k": 4747,
    "ka": 1501,
    "ke": 1708,
    "ko": 613,
    "ku": 924,
    " l": 13610,
    "la": 2372,
    "le": 3298,
    "li": 6048,
    "lo": 192,
    "lu": 1258,
    "lv": 441,
    "v ": 603,
    "ve": 84,
    " m": 8588,
    "ma": 1239,
    "me": 3834,
    "mi": 2474,
    "mo": 508,
    "mu": 533,
    " n": 5933,
    "na": 1773,
    "ne": 1321,
    "ni": 2269,
    "no": 171,
    "nu": 154,
    "nv": 246,
    " o": 90,
    " p": 2821,
    "pa": 705,
    "pe": 305,
    "pi": 1396,
    "po": 236,
    "pu": 180,
    " q": 7929,
    "qi": 5602,
    "qu": 2327,
    " r": 5997,
    "ra": 939,
    "re": 3219,
    "ri": 475,
    "ro": 274,
    "ru": 1091,
    " s": 23469,
    "sa": 670,
    "se": 250,
    "sh": 19164,
    "si": 1378,
    "so": 237,
    "su": 1770,
    " t": 9695,
    "ta": 4285,
    "te": 347,
    "ti": 2393,
    "to": 1709,
    "tu": 960,
    " w": 9482,
    "wa": 1759,
    "we": 3650,
    "wo": 2283,
    "wu": 1791,
    " x": 13227,
    "xi": 11259,
    "xu": 1968,
    " y": 23722,
    "ya": 3611,
    "ye": 1619,
    "yi": 9550,
    "yo": 4440,
    "yu": 4501,
    " z": 25459,
    "za": 3503,
    "ze": 673,
    "zh": 16392,
    "zi": 2074,
    "zo": 626,
    "zu": 2190
  }
}
